ngrad/__init__.py
ngrad/engine.py
ngrad/library.py
ngrad-1.0.1.dist-info/LICENSE
ngrad-1.0.1.dist-info/METADATA
ngrad-1.0.1.dist-info/WHEEL
ngrad-1.0.1.dist-info/top_level.txt
ngrad-1.0.1.dist-info/RECORD
