Metadata-Version: 2.1
Name: ngrad
Version: 1.0.1
Summary: An Autograd engine and a neural network library that handle an N-dimensional array.
Home-page: https://github.com/x0axz/ngrad
Author: Nooh
Author-email: x0axz@protonmail.com
License: UNKNOWN
Platform: UNKNOWN
Classifier: Programming Language :: Python :: 3
Classifier: License :: OSI Approved :: MIT License
Classifier: Operating System :: OS Independent
Requires-Python: >=3.6
License-File: LICENSE
Requires-Dist: numpy
